nasem_dairy/__init__.py
nasem_dairy/dag/ModelDAG.py
nasem_dairy/dag/__init__.py
nasem_dairy/data/__init__.py
nasem_dairy/data/constants.py
nasem_dairy/data/demo/calf_starter_feed.json
nasem_dairy/data/demo/dry_cow.json
nasem_dairy/data/demo/dry_cow_grazing.json
nasem_dairy/data/demo/dry_cow_late_gestation.json
nasem_dairy/data/demo/jersey_heifer.json
nasem_dairy/data/demo/lactating_cow_early_lactation.json
nasem_dairy/data/demo/lactating_cow_other.json
nasem_dairy/data/demo/lactating_cow_test.csv
nasem_dairy/data/demo/lactating_cow_test.json
nasem_dairy/data/feed_library/NASEM_feed_library.csv
nasem_dairy/model/__init__.py
nasem_dairy/model/input_definitions.py
nasem_dairy/model/input_validation.py
nasem_dairy/model/nasem.py
nasem_dairy/model/utility.py
nasem_dairy/model_output/ModelOutput.py
nasem_dairy/model_output/__init__.py
nasem_dairy/model_output/model_output_structure.json
nasem_dairy/model_output/report_structure.json
nasem_dairy/nasem_equations/__init__.py
nasem_dairy/nasem_equations/amino_acid.py
nasem_dairy/nasem_equations/animal.py
nasem_dairy/nasem_equations/body_composition.py
nasem_dairy/nasem_equations/coefficient_adjustment.py
nasem_dairy/nasem_equations/dry_matter_intake.py
nasem_dairy/nasem_equations/energy_requirement.py
nasem_dairy/nasem_equations/fecal.py
nasem_dairy/nasem_equations/gestation.py
nasem_dairy/nasem_equations/infusion.py
nasem_dairy/nasem_equations/manure.py
nasem_dairy/nasem_equations/methane.py
nasem_dairy/nasem_equations/microbial_protein.py
nasem_dairy/nasem_equations/micronutrient_requirement.py
nasem_dairy/nasem_equations/milk.py
nasem_dairy/nasem_equations/nutrient_intakes.py
nasem_dairy/nasem_equations/protein.py
nasem_dairy/nasem_equations/protein_requirement.py
nasem_dairy/nasem_equations/report.py
nasem_dairy/nasem_equations/rumen.py
nasem_dairy/nasem_equations/urine.py
nasem_dairy/nasem_equations/water.py
nasem_dairy/sensitivity/DatabaseManager.py
nasem_dairy/sensitivity/SensitivityAnalyzer.py
nasem_dairy-1.0.2.dist-info/LICENSE
nasem_dairy-1.0.2.dist-info/LICENSE-R_Code
nasem_dairy-1.0.2.dist-info/METADATA
nasem_dairy-1.0.2.dist-info/WHEEL
nasem_dairy-1.0.2.dist-info/RECORD
