Metadata-Version: 2.1
Name: nasem_dairy
Version: 1.0.2
Summary: Implementation of the NASEM Nutrient Requirements of Dairy Cattle 8th Edition in Python
License: MIT
Author: Braeden Fieguth & David Innes
Requires-Python: >=3.9,<4.0
Classifier: License :: OSI Approved :: MIT License
Classifier: Programming Language :: Python :: 3
Classifier: Programming Language :: Python :: 3.9
Classifier: Programming Language :: Python :: 3.10
Classifier: Programming Language :: Python :: 3.11
Classifier: Programming Language :: Python :: 3.12
Provides-Extra: dag
Requires-Dist: importlib-resources (>=6.4.0,<7.0.0)
Requires-Dist: numpy (>=1.25.1,<2.0.0)
Requires-Dist: pandas (>=2.0.3,<3.0.0)
Requires-Dist: pytest (>=7.4.4,<8.0.0)
Requires-Dist: pytest-cov (>=5.0.0,<6.0.0)
Requires-Dist: salib (>=1.5.1,<2.0.0)
